[{"id":435130578300305400,"posicion":0,"nombre":"Abdo","contador":2,"imagen":"https://instagram.faep9-2.fna.fbcdn.net/v/t51.2885-19/s150x150/154157462_4070429576354393_4473040190788507273_n.jpg?tp=1&_nc_ht=instagram.faep9-2.fna.fbcdn.net&_nc_ohc=xG7R1P0Ga7kAX-j99Vs&edm=ABfd0MgAAAAA&ccb=7-4&oh=54cf5c6c985abe270cd53e5eb4629a51&oe=609C7CB7&_nc_sid=7bff83"},{"id":565704505883099140,"posicion":1,"nombre":"Uri","contador":0,"imagen":"https://instagram.faep9-2.fna.fbcdn.net/v/t51.2885-19/s150x150/102259154_592941951327101_7769805218847712953_n.jpg?tp=1&_nc_ht=instagram.faep9-2.fna.fbcdn.net&_nc_ohc=WjDrGWit4wsAX-YkBAU&edm=ABfd0MgAAAAA&ccb=7-4&oh=2d268aeaff1912ef57144d5c0f662056&oe=609E1B12&_nc_sid=7bff83"},{"id":690543365879627800,"posicion":2,"nombre":"Chino","contador":0,"imagen":"https://instagram.faep9-2.fna.fbcdn.net/v/t51.2885-19/s150x150/166171697_905541590243067_1154883512845640397_n.jpg?tp=1&_nc_ht=instagram.faep9-2.fna.fbcdn.net&_nc_ohc=yCMS2gCB4S4AX9Rvh_j&edm=ABfd0MgAAAAA&ccb=7-4&oh=841e536ad88aa45addf01ce298dc3e4e&oe=609D67CB&_nc_sid=7bff83"},{"id":585937899850301400,"posicion":3,"nombre":"Galo","contador":0,"imagen":"https://instagram.faep9-2.fna.fbcdn.net/v/t51.2885-19/s150x150/93069680_216212713017613_4493485000863252480_n.jpg?tp=1&_nc_ht=instagram.faep9-2.fna.fbcdn.net&_nc_ohc=YjsDrK1bprIAX_amEPi&edm=ABfd0MgAAAAA&ccb=7-4&oh=8f3f0e2c5b0c3ab68f4b7cebf347aa40&oe=609C7E58&_nc_sid=7bff83"},{"id":465922433963130900,"posicion":4,"nombre":"Manu","contador":0,"imagen":"https://instagram.faep9-2.fna.fbcdn.net/v/t51.2885-19/s150x150/82845282_126346448799937_2067408397992460288_n.jpg?tp=1&_nc_ht=instagram.faep9-2.fna.fbcdn.net&_nc_ohc=X8wJKGqxRh0AX-0JjQX&edm=ABfd0MgAAAAA&ccb=7-4&oh=9562f580c64c45e266847b2188e4f35a&oe=609EDE99&_nc_sid=7bff83"},{"id":186184495941156860,"posicion":5,"nombre":"Chori","contador":2,"imagen":"https://instagram.faep9-2.fna.fbcdn.net/v/t51.2885-19/s150x150/167597858_261769275682392_4397562762848428435_n.jpg?tp=1&_nc_ht=instagram.faep9-2.fna.fbcdn.net&_nc_ohc=H66jzbVfBIQAX-QTgcu&edm=ABfd0MgAAAAA&ccb=7-4&oh=ce8fc01ef9aa313c3b2543f186397c61&oe=609E90FF&_nc_sid=7bff83"},{"id":690545326716747800,"posicion":6,"nombre":"Luka","contador":0,"imagen":"https://instagram.faep9-2.fna.fbcdn.net/v/t51.2885-19/s150x150/149311356_1812766955557412_78014569395917494_n.jpg?tp=1&_nc_ht=instagram.faep9-2.fna.fbcdn.net&_nc_ohc=PBi_r4Zf_5YAX9vXCWG&edm=ABfd0MgAAAAA&ccb=7-4&oh=0a0ef247614b99bf7519d2fd0798ba9f&oe=609D4884&_nc_sid=7bff83"},{"id":480482890837131260,"posicion":7,"nombre":"Franco","contador":0,"imagen":"https://instagram.faep9-2.fna.fbcdn.net/v/t51.2885-19/s150x150/166035714_451334056134996_2353200363259714644_n.jpg?tp=1&_nc_ht=instagram.faep9-2.fna.fbcdn.net&_nc_ohc=DVUUWgYhzrUAX8OJ-Z_&edm=ABfd0MgAAAAA&ccb=7-4&oh=fb7eff13d8d140974a5a124b6e5e94a2&oe=609DEA63&_nc_sid=7bff83"},{"id":391065505378730000,"posicion":8,"nombre":"Alan","contador":0,"imagen":"https://instagram.faep9-2.fna.fbcdn.net/v/t51.2885-19/s150x150/144877991_478045076521407_3823747482129141250_n.jpg?tp=1&_nc_ht=instagram.faep9-2.fna.fbcdn.net&_nc_ohc=cH7kfX7Gn8QAX8_kclR&edm=ABfd0MgAAAAA&ccb=7-4&oh=19d2e9c33ca882a78b01a671e5a6cdee&oe=609EC7DF&_nc_sid=7bff83"},{"id":436651544801443840,"posicion":9,"nombre":"Tobi","contador":0,"imagen":"https://instagram.faep9-2.fna.fbcdn.net/v/t51.2885-19/s150x150/172677388_3039870362925212_3558350983656682751_n.jpg?tp=1&_nc_ht=instagram.faep9-2.fna.fbcdn.net&_nc_ohc=fSMgEtZcv8sAX_t8stA&edm=AHG7ALcAAAAA&ccb=7-4&oh=7e5746cea516f23fdde78c0546d7442b&oe=609D3A09&_nc_sid=5cbaad"},{"id":456886030184874000,"posicion":10,"nombre":"Marto","contador":0,"imagen":"https://instagram.faep9-2.fna.fbcdn.net/v/t51.2885-19/s150x150/26866629_2199205096980020_829907098857897984_n.jpg?tp=1&_nc_ht=instagram.faep9-2.fna.fbcdn.net&_nc_ohc=IDtH3y-nlo8AX-36Pyg&edm=ABfd0MgAAAAA&ccb=7-4&oh=9eb0e4d48f9f4c30e78ae1994353a486&oe=609F67C8&_nc_sid=7bff83"}]